{
    "songs": [
        {
            "albumart": "https://lh3.googleusercontent.com/QYbsINoGU9I21SDVPyluHD3Sv5anfENbnvyQ6C5FSN0nxWBz9PHqcFW9H-kzjiYhWviRaaLjyHFM0a1M=w544-h544-l90-rj",
            "author": "Macklemore & Ryan Lewis ft Wanz",
            "song": "Thrift Shop",
            "json": "https://tune-radio.github.io/lyric/hiphop/Macklemore%20%26%20Ryan%20Lewis%20ft%20Wanz%20-%20Thrift%20Shop.json",
            "audio": "https://tune-radio.github.io/hiphop/Macklemore%20%26%20Ryan%20Lewis%20ft%20Wanz%20-%20Thrift%20Shop.ogg"
        },
        {
            "albumart": "https://lh3.googleusercontent.com/IUuZFSUqFLMQlejTtsnLM_cB16A0T1g-savL7DYbWz5NFh2-DOw5-v9_PREJt9keX48NSan-8yUQCPM=w544-h544-l90-rj",
            "author": "Eminem ft Rihanna",
            "song": "Love The Way you Lie",
            "json": "https://tune-radio.github.io/lyric/hiphop/Eminem%20ft%20Rihanna%20-%20Love%20The%20Way%20You%20Lie.json",
            "audio": "https://tune-radio.github.io/hiphop/Eminem%20ft%20Rihanna%20-%20Love%20The%20Way%20You%20Lie.ogg"
        },
        {
            "albumart": "https://lh3.googleusercontent.com/8RzTEcJkaD6FwVFocRUr6_iJqkUNIeKh5w1g_7QwgFvr1JWSRm-dH1muhqBpFTArCgvW0VtRuF9Kny_e=w544-h544-l90-rj",
            "author": "Eminem ft Rihanna",
            "song": "The Monster",
            "json": "https://tune-radio.github.io/lyric/hiphop/Eminem%20ft%20Rihanna%20-%20The%20Monster.json",
            "audio": "https://tune-radio.github.io/hiphop/Eminem%20ft%20Rihanna%20-%20The%20Monster.ogg"
        },
        {
            "albumart": "https://lh3.googleusercontent.com/IUuZFSUqFLMQlejTtsnLM_cB16A0T1g-savL7DYbWz5NFh2-DOw5-v9_PREJt9keX48NSan-8yUQCPM=w544-h544-l90-rj",
            "author": "Eminem",
            "song": "Cinderella Man",
            "json": "https://tune-radio.github.io/lyric/hiphop/Eminem%20-%20Cinderella%20Man.json",
            "audio": "https://tune-radio.github.io/hiphop/Eminem%20-%20Cinderella%20Man.ogg"
        },
        {
            "albumart": "https://lh3.googleusercontent.com/1zJQeKEbH6zGFD_SnFiiMBrWvDNaCx_tNbH4AbgyjtKffdrd-sAHqyaMHmj1WTApvKyFupA5mJ192u_T=w544-h544-l90-rj",
            "author": "Lil Nas X",
            "song": "Industry Baby",
            "json": "https://tune-radio.github.io/lyric/hiphop/Lil%20Nas%20X%20-%20Industry%20Baby.json",
            "audio": "https://tune-radio.github.io/hiphop/Lil%20Nas%20X%20-%20Industry%20Baby.ogg"
        },
        {
            "albumart": "https://lh3.googleusercontent.com/8wTSftJOtEIf3iqBJq_HfPzLYiN8ni4QymjSwCHRfYw-mSClbmimIb0o9GW7FZYLb0S1aFYz16pHmjjcYA=w544-h544-l90-rj",
            "author": "Lil Nas X",
            "song": "Thas What I Want",
            "json": "https://tune-radio.github.io/lyric/hiphop/Lil%20Nas%20X%20-%20Thats%20What%20I%20Want.json",
            "audio": "https://tune-radio.github.io/hiphop/Lil%20Nas%20X%20-%20Thats%20What%20I%20Want.ogg"
        },
        {
            "albumart": "https://lh3.googleusercontent.com/w42BmVN1uTez5YI99RhuHvk4u_Eoj6LeXg7d-HMP4c5IkZ5XJbD_04suECGSRw0a6TBdU8UgwRNlDt3lQQ=w544-h544-s-l90-rj",
            "author": "Dr Dre ft Snoop Dogg",
            "song": "Still D.R.E.",
            "json": "https://tune-radio.github.io/lyric/hiphop/Dr%20Dre%20ft%20Snoop%20Dogg%20-%20Still%20D.R.json",
            "audio": "https://tune-radio.github.io/hiphop/Dr%20Dre%20ft%20Snoop%20Dogg%20-%20Still%20D.R.ogg"
        },
        {
            "albumart": "https://lh3.googleusercontent.com/lD_dZCseNDPPqZkboCBhIrLy53GoC4mmL5SJyXqWo_xwjjyyCRONuu5ceZaUrcQRpozSxCK32ZcL9tKM=w544-h544-l90-rj",
            "author": "Juice WRLD",
            "song": "Lucid Dreams",
            "json": "https://tune-radio.github.io/lyric/hiphop/Juice%20WRLD%20-%20Lucid%20Dreams.json",
            "audio": "https://tune-radio.github.io/hiphop/Juice%20WRLD%20-%20Lucid%20Dreams.ogg"
        },
        {
            "albumart": "https://lh3.googleusercontent.com/GJmbTYfaMrWuPSzhOAy7jGCQ70a2UN2-0moTq-uh_Prd73-Au51FDHhGteg543a7iBv1Y9SPm4huMSBS=w544-h544-s-l90-rj",
            "author": "Eminem",
            "song": "Without Me",
            "json": "https://tune-radio.github.io/lyric/hiphop/Eminem%20-%20Without%20Me.json",
            "audio": "https://tune-radio.github.io/hiphop/Eminem%20-%20Without%20Me.ogg"
        },
        {
            "albumart": "https://lh3.googleusercontent.com/b-euORTq-_MSzc3SyI0QOjLqnCBJbWuMmH1YlyJKAVvJfOpPqv3bFH-KSDoQwV9e8Xey1X2NRo9xZ2U=w544-h544-l90-rj",
            "author": "Eminem ft Ed Sheeran",
            "song": "River",
            "json": "https://tune-radio.github.io/lyric/hiphop/Eminem%20ft%20Ed%20Sheeran%20-%20River.json",
            "audio": "https://tune-radio.github.io/hiphop/Eminem%20ft%20Ed%20Sheeran%20-%20River.ogg"
        },
        {
            "albumart": "https://lh3.googleusercontent.com/xs4mteyXvx8duO_IP_egUiNfC-MNmrtQVbe1wAWL5fBmXJY5roPRSwH-5GNJu8g3SdhI8DggG3ixp5O1yw=w544-h544-l90-rj",
            "author": "Section D'Assaut",
            "song": "Désolé",
            "json": "https://tune-radio.github.io/lyric/hiphop/Section%20D'Assaut%20-%20D%C3%A9sol%C3%A9.json",
            "audio": "https://tune-radio.github.io/hiphop/Section%20D'Assaut%20-%20D%C3%A9sol%C3%A9.ogg"
        },
        {
            "albumart": "https://lh3.googleusercontent.com/flyz4zMaaZoeEFOdyKnfDhddZuoJKDbf_wGuCa9xD9tyf6LmzQJf7CoYPE1Pq7JDBk1leKkDvnH0LQ=w544-h544-s-l90-rj",
            "author": "Section D'Assaut",
            "song": "Ma Direction",
            "json": "https://tune-radio.github.io/lyric/hiphop/Section%20D'Assaut%20-%20Ma%20direction.json",
            "audio": "https://tune-radio.github.io/hiphop/Section%20D'Assaut%20-%20Ma%20direction.ogg"
        },
        {
            "albumart": "https://lh3.googleusercontent.com/8Z0dgKaWgJXU8to3VXaVy3wFk8fzx5lOTl1BJgU31iBIImNsXRnjKA8jYdcabR-3YPdj1UOGnEXK3Gqj=w544-h544-l90-rj",
            "author": "Yanns",
            "song": "Clic clic pan pan",
            "json": "https://tune-radio.github.io/lyric/hiphop/Yanns%20-%20Clic%20clic%20pan%20pan.json",
            "audio": "https://tune-radio.github.io/hiphop/Yanns%20-%20Clic%20clic%20pan%20pan.ogg"
        },
        {
            "albumart": "https://lh3.googleusercontent.com/ki10CgjUQMxjdLLuHDgtSAJPUVcvnsjrF6y1aaM5hiqRySJDX0PGLcjqT49_gKLtK9Xwd-h1hCiYc_PyIQ=w544-h544-l90-rj",
            "author": "Gazo",
            "song": "Die",
            "json": "https://tune-radio.github.io/lyric/hiphop/Gazzo%20-%20DIE.json",
            "audio": "https://tune-radio.github.io/hiphop/Gazzo%20-%20DIE.ogg"
        },
        {
            "albumart": "https://lh3.googleusercontent.com/kwVrk8cP08YKCeXIuC29gR_GFl593fxfXc_2E1O4XgBZ9cxCtY7CEyM782X8APdp1mTdm8cnAcLEOME=w544-h544-l90-rj",
            "author": "Orelsan ft Damso",
            "song": "Rêves Bizarres",
            "json": "https://tune-radio.github.io/lyric/hiphop/Orelsan%20ft%20Damso%20-%20R%C3%AAves%20bizarres.json",
            "audio": "https://tune-radio.github.io/hiphop/Orelsan%20ft%20Damso%20-%20R%C3%AAves%20bizarres.ogg"
        },
        {
            "albumart": "https://lh3.googleusercontent.com/7fv4T1d9OdcT8aMiK0pBwb2ittpMmgDQ1LhvymGa6dAkyA_E1m5JgqSWg6GMZLJXR0YtR44KxYJ1bSzo=w544-h544-l90-rj",
            "author": "Zeg G ft Hamza & SCH",
            "song": "Fade UP",
            "json": "https://tune-radio.github.io/lyric/hiphop/Zeg%20P%20ft%20Hamza%20&%20SCH%20-%20Fade%20UP.json",
            "audio": "https://tune-radio.github.io/hiphop/Zeg%20P%20ft%20Hamza%20&%20SCH%20-%20Fade%20UP.ogg"
        },
        {
            "albumart": "https://lh3.googleusercontent.com/lmMgp62lnrYGKHARAf9bMM-gQo9pbuzHfPIzSUB_1zzEEd6HnlPocms_Rs2Jq_u4khUNTwTW6e7XalJd=w544-h544-l90-rj",
            "author": "Alonzo ft Ninho & Naps",
            "song": "Tout Va Bien",
            "json": "https://tune-radio.github.io/lyric/hiphop/Alonzo%20ft%20Ninho%20%26%20Naps%20-%20Tout%20Va%20Bien.json",
            "audio": "https://tune-radio.github.io/hiphop/Alonzo%20ft%20Ninho%20%26%20Naps%20-%20Tout%20Va%20Bien.ogg"
        },
        {
            "albumart": "https://lh3.googleusercontent.com/pmV4MeRssAf-cmB3GbdLwHdgQok105S26JCOWYiDNewgvasdpbReZRKKiiCn87Kt_18mpu-K8ZeaCaqxlA=w544-h544-l90-rj",
            "author": "Naps",
            "song": "La kiffance",
            "json": "https://tune-radio.github.io/lyric/hiphop/Naps%20-%20La%20kiffance.json",
            "audio": "https://tune-radio.github.io/hiphop/Naps%20-%20La%20kiffance.ogg"
        },
        {
            "albumart": "https://lh3.googleusercontent.com/d839QAhSoC58LRIEOZXApz5FIlNKtExVa_AHfQ8wGRI24OU3jmDhBBJIi2sFE-hSLJHRLp0h25di4hXg=w544-h544-l90-rj",
            "author": "Ninho",
            "song": "La vie qu'on mêne",
            "json": "https://tune-radio.github.io/lyric/hiphop/Ninho%20-%20La%20vie%20qu%20on%20m%C3%A8ne.json",
            "audio": "https://tune-radio.github.io/hiphop/Ninho%20-%20La%20vie%20qu%20on%20m%C3%A8ne.ogg"
        },
        {
            "albumart": "https://lh3.googleusercontent.com/U8mlOryQ4GFNyR0PPOXaZG-aDmrxqN6x6ejZ-iIJ8xKpFxImCl7Ex5vn6_IK_NPNzhV7aOknrNAWkPCZ=w544-h544-l90-rj",
            "author": "Chiloo",
            "song": "Bipolaire",
            "json": "https://tune-radio.github.io/lyric/hiphop/Chiloo%20-%20Bipolaire.json",
            "audio": "https://tune-radio.github.io/hiphop/Chiloo%20-%20Bipolaire.ogg"
        }
    ]
}
